{
    "id": "footer_section",
    "name": "Footer Section",
    "version": "1.0",
    "date": "24-03-2024T23:54",
    "data": [
        {
            "id": "bloggios__section",
            "section": "Bloggios",
            "links": [
                {
                    "id": "bg__l1",
                    "label": "Home",
                    "path": "/home"
                },
                {
                    "id": "bg__l2",
                    "label": "Post",
                    "path": "/post"
                },
                {
                    "id": "bg__l3",
                    "label": "Q&A",
                    "path": "/question"
                },
                {
                    "id": "bg__l4",
                    "label": "Messaging",
                    "path": "/chats"
                }
            ]
        },
        {
            "id": "services__section",
            "section": "Services",
            "links": [
                {
                    "id": "bg__service__l1",
                    "label": "Product Development",
                    "path": "/services/product-development"
                },
                {
                    "id": "bg__service__l2",
                    "label": "Product Ideation",
                    "path": "/services#productIdeationServicePageSection"
                },
                {
                    "id": "bg__service__l3",
                    "label": "Technical Support",
                    "path": "/services#technicalSupportServicePageSection"
                },
                {
                    "id": "bg__service__l4",
                    "label": "Tech Training",
                    "path": "/services#technicalExpertServicePageSection"
                }
            ]
        },
        {
            "id": "company__section",
            "section": "Company",
            "links": [
                {
                    "id": "bg__company__l1",
                    "label": "Landing",
                    "path": "/"
                },
                {
                    "id": "bg__company__l2",
                    "label": "Bloggios Tech",
                    "path": "/services"
                },
                {
                    "id": "bg__company__l3",
                    "label": "Report Bug",
                    "path": "/report-bug"
                },
                {
                    "id": "bg__company__l4",
                    "label": "Support",
                    "path": "/support"
                }
            ]
        }
    ]
}